gitbatch/__init__.py
gitbatch/cli.py
gitbatch/logging.py
"gitbatch/test/__init__,py"
gitbatch/test/unit/test_cli.py
gitbatch/test/unit/test_copy.py
gitbatch/utils/__init__.py
gitbatch/utils/copy.py
git_batch-5.1.3.dist-info/METADATA
git_batch-5.1.3.dist-info/WHEEL
git_batch-5.1.3.dist-info/entry_points.txt
git_batch-5.1.3.dist-info/licenses/LICENSE
git_batch-5.1.3.dist-info/RECORD
