Metadata-Version: 2.4
Name: git-batch
Version: 5.1.3
Summary: Clone single branch from all repositories listed in a file.
License: MIT
License-File: LICENSE
Keywords: git,batch,automation
Author: Robert Kaussow
Author-email: mail@thegeeklab.de
Requires-Python: >=3.11.0,<4.0.0
Classifier: Development Status :: 5 - Production/Stable
Classifier: Environment :: Console
Classifier: Intended Audience :: Developers
Classifier: Intended Audience :: Information Technology
Classifier: Intended Audience :: System Administrators
Classifier: License :: OSI Approved :: MIT License
Classifier: Natural Language :: English
Classifier: Operating System :: POSIX
Classifier: Programming Language :: Python :: 3
Classifier: Programming Language :: Python :: 3.11
Classifier: Programming Language :: Python :: 3.12
Classifier: Programming Language :: Python :: 3.13
Classifier: Programming Language :: Python :: 3.14
Classifier: Topic :: Software Development
Classifier: Topic :: Utilities
Requires-Dist: GitPython (==3.1.46)
Requires-Dist: colorama (==0.4.6)
Requires-Dist: python-json-logger (==4.0.0)
Project-URL: Documentation, https://github.com/thegeeklab/git-batch/
Project-URL: Homepage, https://github.com/thegeeklab/git-batch/
Project-URL: Repository, https://github.com/thegeeklab/git-batch/
